xiaoliupackage/__init__.py
xiaoliupackage/package1/__init__.py
xiaoliupackage/package1/module1.py
xiaoliupackage/package1/module2.py
xiaoliupackage/package1/package2/module1.py
xiaoliupackage/package3/__init__.py
xiaoliupackage/package3/module1.py
xiaoliupackage-0.0.7.1.dist-info/METADATA
xiaoliupackage-0.0.7.1.dist-info/WHEEL
xiaoliupackage-0.0.7.1.dist-info/top_level.txt
xiaoliupackage-0.0.7.1.dist-info/RECORD
