Metadata-Version: 2.2
Name: xiaoliupackage
Version: 0.0.7.1
Summary: My first Python package
Author-email: Liu <xaliu@dolby.com>
License: Attempy free
Classifier: Development Status :: 3 - Alpha
Classifier: Programming Language :: Python :: 3
Classifier: Operating System :: MacOS :: MacOS X
Classifier: Operating System :: Microsoft :: Windows
Requires-Python: >=3
